AutoLayout/__init__.py
AutoLayout/autopacker.py
AutoLayout/expSet.py
AutoLayout/layout.py
AutoLayout/numCodeGenerator.py
AutoLayout/regionUtils.py
AutoLayout-1.0.dist-info/METADATA
AutoLayout-1.0.dist-info/WHEEL
AutoLayout-1.0.dist-info/top_level.txt
AutoLayout-1.0.dist-info/RECORD
