Metadata-Version: 2.1
Name: AutoLayout
Version: 1.0
Home-page: https://github.com/trezitorul/GDSPYUtils/tree/AutoLayout-package/AutoLayout
Author: Tin Tran
Author-email: trantin0815@gmail.com
License: MIT
Keywords: AutoLayout
Requires-Dist: rectpack
Requires-Dist: gdspy
Requires-Dist: openpyxl
